rapid_dev_storage/__init__.py
rapid_dev_storage/_base_api.py
rapid_dev_storage/_sqlite_backend.py
rapid_dev_storage/_types.py
rapid_dev_storage-1.0.0.dist-info/LICENSE
rapid_dev_storage-1.0.0.dist-info/METADATA
rapid_dev_storage-1.0.0.dist-info/WHEEL
rapid_dev_storage-1.0.0.dist-info/top_level.txt
rapid_dev_storage-1.0.0.dist-info/RECORD
