Metadata-Version: 2.1
Name: rapid-dev-storage
Version: 1.0.0
Summary: A simple, but effective storage mechanism for rapid development
Home-page: https://github.com/mikeshardmind/rapid_dev_storage
Author: Michael Hall
Author-email: michael@michaelhall.tech
License: MIT
Platform: UNKNOWN
Requires-Python: >=3.8
Requires-Dist: apsw-wheels
Requires-Dist: msgpack
